taegis_sdk_python/__init__.py
taegis_sdk_python/_consts.py
taegis_sdk_python/_version.py
taegis_sdk_python/authentication.py
taegis_sdk_python/config.py
taegis_sdk_python/errors.py
taegis_sdk_python/service_core.py
taegis_sdk_python/tokens.py
taegis_sdk_python/utils.py
taegis_sdk_python/commons/__init__.py
taegis_sdk_python/commons/alerts/__init__.py
taegis_sdk_python/commons/alerts/federated_search.py
taegis_sdk_python/commons/alerts/search.py
taegis_sdk_python/commons/cases/__init__.py
taegis_sdk_python/commons/cases/federated_search.py
taegis_sdk_python/commons/cases/search.py
taegis_sdk_python/commons/events/__init__.py
taegis_sdk_python/commons/events/search.py
taegis_sdk_python/commons/investigations/__init__.py
taegis_sdk_python/commons/investigations/federated_search.py
taegis_sdk_python/commons/investigations/search.py
taegis_sdk_python/commons/sharelinks/__init__.py
taegis_sdk_python/commons/sharelinks/create.py
taegis_sdk_python/commons/sharelinks/unfurl.py
taegis_sdk_python/middlewares/__init__.py
taegis_sdk_python/middlewares/utils.py
taegis_sdk_python/middlewares/logging/__init__.py
taegis_sdk_python/middlewares/logging/_default.py
taegis_sdk_python/middlewares/retry/__init__.py
taegis_sdk_python/middlewares/retry/_default.py
taegis_sdk_python/services/__init__.py
taegis_sdk_python/services/access_points/__init__.py
taegis_sdk_python/services/access_points/mutations.py
taegis_sdk_python/services/access_points/queries.py
taegis_sdk_python/services/access_points/subscriptions.py
taegis_sdk_python/services/access_points/types.py
taegis_sdk_python/services/agent/__init__.py
taegis_sdk_python/services/agent/mutations.py
taegis_sdk_python/services/agent/queries.py
taegis_sdk_python/services/agent/subscriptions.py
taegis_sdk_python/services/agent/types.py
taegis_sdk_python/services/alerts/__init__.py
taegis_sdk_python/services/alerts/mutations.py
taegis_sdk_python/services/alerts/queries.py
taegis_sdk_python/services/alerts/subscriptions.py
taegis_sdk_python-1.6.9.1.dist-info/METADATA
taegis_sdk_python-1.6.9.1.dist-info/WHEEL
taegis_sdk_python-1.6.9.1.dist-info/licenses/LICENSE
taegis_sdk_python-1.6.9.1.dist-info/RECORD
