Metadata-Version: 2.4
Name: taegis-sdk-python
Version: 1.6.9.1
Summary: Taegis Python SDK
Project-URL: Homepage, https://github.com/secureworks/taegis-sdk-python
Project-URL: Bug Reports, https://github.com/secureworks/taegis-sdk-python/issues
Project-URL: Source, https://github.com/secureworks/taegis-sdk-python
Project-URL: Package, https://pypi.org/project/taegis-sdk-python/
Author-email: Micah Pegman <sdks@secureworks.com>
License:                                  Apache License
License-File: LICENSE
Classifier: License :: OSI Approved :: Apache Software License
Classifier: Operating System :: OS Independent
Classifier: Programming Language :: Python :: 3
Classifier: Programming Language :: Python :: 3.9
Classifier: Programming Language :: Python :: 3.10
Classifier: Programming Language :: Python :: 3.11
Classifier: Programming Language :: Python :: 3.12
Classifier: Programming Language :: Python :: 3.13
Requires-Python: >=3.9
Requires-Dist: aiohttp
Requires-Dist: backoff
Requires-Dist: dataclasses-json
Requires-Dist: filelock>=3.12.4
Requires-Dist: gql>=4
Requires-Dist: graphql-core
Requires-Dist: jinja2
Requires-Dist: oauthlib
Requires-Dist: pyjwt>=2.8.0
Requires-Dist: python-dateutil
Requires-Dist: requests
Requires-Dist: requests-oauthlib
Requires-Dist: requests-toolbelt
Requires-Dist: websockets
Provides-Extra: dev
Requires-Dist: black; extra == 'dev'
Requires-Dist: pylint==3.2.3; extra == 'dev'
Provides-Extra: test
Requires-Dist: coverage; extra == 'test'
Requires-Dist: pytest; extra == 'test'
Requires-Dist: pytest-cov; extra == 'test'
Requires-Dist: pytest-mock; extra == 'test'
